{
  "gsd": {
    "metadata": {
      "type": "concern",
      "exploitCode": "unknown",
      "remediation": "official",
      "reportConfidence": "confirmed",
      "reporter": "joshbressers",
      "reporter_id": "1692786"
    },
    "osvSchema": {
      "id": "GSD-2023-1006658",
      "modified": "2023-06-07T21:59:26.418410Z",
      "published": "2023-06-07T21:59:26.418410Z",
      "schema_version": "1.4.0",
      "summary": "ACPICA: Avoid undefined behavior: applying zero offset to null pointer",
      "details": "ACPICA: Avoid undefined behavior: applying zero offset to null pointer\n\nThis is an automated ID intended to aid in discovery of potential security vulnerabilities. The actual impact and attack plausibility have not yet been proven.\nThis ID is fixed in Linux Kernel version v5.4.244 by commit 710e09fd116e2fa53e319a416ad4e4f8027682b6. For more details please see the references link.",
      "affected": [
        {
          "package": {
            "name": "Kernel",
            "ecosystem": "Linux"
          },
          "ranges": [
            {
              "type": "GIT",
              "repo": "https://git.kernel.org/pub/scm/linux/kernel/git/stable/linux.git/",
              "events": [
                {
                  "introduced": "0"
                },
                {
                  "limit": "710e09fd116e2fa53e319a416ad4e4f8027682b6"
                }
              ]
            },
            {
              "type": "SEMVER",
              "repo": "https://git.kernel.org/pub/scm/linux/kernel/git/stable/linux.git/",
              "events": [
                {
                  "introduced": "0"
                },
                {
                  "fixed": "5.4.244"
                }
              ]
            }
          ]
        }
      ],
      "references": [
        {
          "type": "FIXED",
          "url": "https://git.kernel.org/pub/scm/linux/kernel/git/stable/linux.git/commit/?id=710e09fd116e2fa53e319a416ad4e4f8027682b6"
        }
      ]
    }
  }
}
