{
  "gsd": {
    "metadata": {
      "type": "concern",
      "exploitCode": "unknown",
      "remediation": "official",
      "reportConfidence": "confirmed",
      "reporter": "joshbressers",
      "reporter_id": "1692786"
    },
    "osvSchema": {
      "id": "GSD-2023-1006917",
      "modified": "2023-06-07T22:30:42.906397Z",
      "published": "2023-06-07T22:30:42.906397Z",
      "schema_version": "1.4.0",
      "summary": "media: dm1105: Fix use after free bug in dm1105_remove due to race condition",
      "details": "media: dm1105: Fix use after free bug in dm1105_remove due to race condition\n\nThis is an automated ID intended to aid in discovery of potential security vulnerabilities. The actual impact and attack plausibility have not yet been proven.\nThis ID is fixed in Linux Kernel version v4.14.315 by commit df01f9c146ce2134de4daf393e29e18d6d5866ec, it was introduced in version v2.6.34 by commit 34d2f9bf189c36ef8642cf6b64e80dfb756d888f. For more details please see the references link.",
      "affected": [
        {
          "package": {
            "name": "Kernel",
            "ecosystem": "Linux"
          },
          "ranges": [
            {
              "type": "GIT",
              "repo": "https://git.kernel.org/pub/scm/linux/kernel/git/stable/linux.git/",
              "events": [
                {
                  "introduced": "34d2f9bf189c36ef8642cf6b64e80dfb756d888f"
                },
                {
                  "limit": "df01f9c146ce2134de4daf393e29e18d6d5866ec"
                }
              ]
            },
            {
              "type": "SEMVER",
              "repo": "https://git.kernel.org/pub/scm/linux/kernel/git/stable/linux.git/",
              "events": [
                {
                  "introduced": "2.6.34"
                },
                {
                  "fixed": "4.14.315"
                }
              ]
            }
          ]
        }
      ],
      "references": [
        {
          "type": "INTRODUCED",
          "url": "https://git.kernel.org/pub/scm/linux/kernel/git/stable/linux.git/commit/?id=34d2f9bf189c36ef8642cf6b64e80dfb756d888f"
        },
        {
          "type": "FIXED",
          "url": "https://git.kernel.org/pub/scm/linux/kernel/git/stable/linux.git/commit/?id=df01f9c146ce2134de4daf393e29e18d6d5866ec"
        }
      ]
    }
  }
}
