{
  "gsd": {
    "metadata": {
      "type": "concern",
      "exploitCode": "unknown",
      "remediation": "official",
      "reportConfidence": "confirmed",
      "reporter": "joshbressers",
      "reporter_id": "1692786"
    },
    "osvSchema": {
      "id": "GSD-2023-1003838",
      "modified": "2023-04-05T02:07:16.477088Z",
      "published": "2023-04-05T02:07:16.477088Z",
      "schema_version": "1.4.0",
      "summary": "net/sched: act_mirred: better wording on protection against excessive stack growth",
      "details": "net/sched: act_mirred: better wording on protection against excessive stack growth\n\nThis is an automated ID intended to aid in discovery of potential security vulnerabilities. The actual impact and attack plausibility have not yet been proven.\nThis ID is fixed in Linux Kernel version v6.1.22 by commit e0c12b9bfffcb56817bb5bada2da9d4a600cd64d. For more details please see the references link.",
      "affected": [
        {
          "package": {
            "name": "Kernel",
            "ecosystem": "Linux"
          },
          "ranges": [
            {
              "type": "GIT",
              "repo": "https://git.kernel.org/pub/scm/linux/kernel/git/stable/linux.git/",
              "events": [
                {
                  "introduced": "0"
                },
                {
                  "limit": "e0c12b9bfffcb56817bb5bada2da9d4a600cd64d"
                }
              ]
            }
          ]
        },
        {
          "package": {
            "name": "Kernel",
            "ecosystem": "Linux"
          },
          "ranges": [
            {
              "type": "SEMVER",
              "repo": "https://git.kernel.org/pub/scm/linux/kernel/git/stable/linux.git/",
              "events": [
                {
                  "introduced": "0"
                },
                {
                  "fixed": "6.1.22"
                }
              ]
            }
          ]
        }
      ],
      "references": [
        {
          "type": "WEB",
          "url": "https://git.kernel.org/pub/scm/linux/kernel/git/stable/linux.git/commit/?id=e0c12b9bfffcb56817bb5bada2da9d4a600cd64d"
        }
      ]
    }
  }
}
