{
  "gsd": {
    "metadata": {
      "type": "concern",
      "exploitCode": "unknown",
      "remediation": "official",
      "reportConfidence": "confirmed",
      "reporter": "joshbressers",
      "reporter_id": "1692786"
    },
    "osvSchema": {
      "id": "GSD-2023-1009933",
      "modified": "2023-12-08T17:19:18.021598Z",
      "published": "2023-12-08T17:19:18.021598Z",
      "schema_version": "1.4.0",
      "summary": "perf stat: Fix aggr mode initialization",
      "details": "perf stat: Fix aggr mode initialization\n\nThis is an automated ID intended to aid in discovery of potential security vulnerabilities. The actual impact and attack plausibility have not yet been proven.\nThis ID is fixed in Linux Kernel version v6.1.63 by commit 550711e007bb77aa47df1b9330cc6159355efb34, it was introduced in version v5.18 by commit 8a96f454f566857290867fb3943ffc37ea7d50d2. For more details please see the references link.",
      "affected": [
        {
          "package": {
            "name": "Kernel",
            "ecosystem": "Linux"
          },
          "ranges": [
            {
              "type": "GIT",
              "repo": "https://git.kernel.org/pub/scm/linux/kernel/git/stable/linux.git/",
              "events": [
                {
                  "introduced": "8a96f454f566857290867fb3943ffc37ea7d50d2"
                },
                {
                  "limit": "550711e007bb77aa47df1b9330cc6159355efb34"
                }
              ]
            },
            {
              "type": "SEMVER",
              "repo": "https://git.kernel.org/pub/scm/linux/kernel/git/stable/linux.git/",
              "events": [
                {
                  "introduced": "5.18"
                },
                {
                  "fixed": "6.1.63"
                }
              ]
            }
          ]
        }
      ],
      "references": [
        {
          "type": "INTRODUCED",
          "url": "https://git.kernel.org/pub/scm/linux/kernel/git/stable/linux.git/commit/?id=8a96f454f566857290867fb3943ffc37ea7d50d2"
        },
        {
          "type": "FIXED",
          "url": "https://git.kernel.org/pub/scm/linux/kernel/git/stable/linux.git/commit/?id=550711e007bb77aa47df1b9330cc6159355efb34"
        }
      ]
    }
  }
}
