{
  "gsd": {
    "metadata": {
      "type": "concern",
      "exploitCode": "unknown",
      "remediation": "official",
      "reportConfidence": "confirmed",
      "reporter": "joshbressers",
      "reporter_id": "1692786"
    },
    "osvSchema": {
      "id": "GSD-2023-1009412",
      "modified": "2023-10-24T22:57:42.891937Z",
      "published": "2023-10-24T22:57:42.891937Z",
      "schema_version": "1.4.0",
      "summary": "mctp: perform route lookups under a RCU read-side lock",
      "details": "mctp: perform route lookups under a RCU read-side lock\n\nThis is an automated ID intended to aid in discovery of potential security vulnerabilities. The actual impact and attack plausibility have not yet been proven.\nThis ID is fixed in Linux Kernel version v6.1.59 by commit 1db0724a01b558feb1ecae551782add1951a114a, it was introduced in version v5.15 by commit 889b7da23abf92faf34491df95733bda63639e32. For more details please see the references link.",
      "affected": [
        {
          "package": {
            "name": "Kernel",
            "ecosystem": "Linux"
          },
          "ranges": [
            {
              "type": "GIT",
              "repo": "https://git.kernel.org/pub/scm/linux/kernel/git/stable/linux.git/",
              "events": [
                {
                  "introduced": "889b7da23abf92faf34491df95733bda63639e32"
                },
                {
                  "limit": "1db0724a01b558feb1ecae551782add1951a114a"
                }
              ]
            },
            {
              "type": "SEMVER",
              "repo": "https://git.kernel.org/pub/scm/linux/kernel/git/stable/linux.git/",
              "events": [
                {
                  "introduced": "5.15"
                },
                {
                  "fixed": "6.1.59"
                }
              ]
            }
          ]
        }
      ],
      "references": [
        {
          "type": "INTRODUCED",
          "url": "https://git.kernel.org/pub/scm/linux/kernel/git/stable/linux.git/commit/?id=889b7da23abf92faf34491df95733bda63639e32"
        },
        {
          "type": "FIXED",
          "url": "https://git.kernel.org/pub/scm/linux/kernel/git/stable/linux.git/commit/?id=1db0724a01b558feb1ecae551782add1951a114a"
        }
      ]
    }
  }
}
