{
  "gsd": {
    "metadata": {
      "type": "concern",
      "exploitCode": "unknown",
      "remediation": "official",
      "reportConfidence": "confirmed",
      "reporter": "joshbressers",
      "reporter_id": "1692786"
    },
    "osvSchema": {
      "id": "GSD-2023-1005621",
      "modified": "2023-06-07T20:08:32.786733Z",
      "published": "2023-06-07T20:08:32.786733Z",
      "schema_version": "1.4.0",
      "summary": "iommufd/selftest: Catch overflow of uptr and length",
      "details": "iommufd/selftest: Catch overflow of uptr and length\n\nThis is an automated ID intended to aid in discovery of potential security vulnerabilities. The actual impact and attack plausibility have not yet been proven.\nThis ID is fixed in Linux Kernel version v6.3.2 by commit 3fb3505636d033bbf7a0851dac63d01732c51d62, it was introduced in version v6.2 by commit f4b20bb34c83dceade5470288f48f94ce3598ada. For more details please see the references link.",
      "affected": [
        {
          "package": {
            "name": "Kernel",
            "ecosystem": "Linux"
          },
          "ranges": [
            {
              "type": "GIT",
              "repo": "https://git.kernel.org/pub/scm/linux/kernel/git/stable/linux.git/",
              "events": [
                {
                  "introduced": "f4b20bb34c83dceade5470288f48f94ce3598ada"
                },
                {
                  "limit": "3fb3505636d033bbf7a0851dac63d01732c51d62"
                }
              ]
            },
            {
              "type": "SEMVER",
              "repo": "https://git.kernel.org/pub/scm/linux/kernel/git/stable/linux.git/",
              "events": [
                {
                  "introduced": "6.2"
                },
                {
                  "fixed": "6.3.2"
                }
              ]
            }
          ]
        }
      ],
      "references": [
        {
          "type": "INTRODUCED",
          "url": "https://git.kernel.org/pub/scm/linux/kernel/git/stable/linux.git/commit/?id=f4b20bb34c83dceade5470288f48f94ce3598ada"
        },
        {
          "type": "FIXED",
          "url": "https://git.kernel.org/pub/scm/linux/kernel/git/stable/linux.git/commit/?id=3fb3505636d033bbf7a0851dac63d01732c51d62"
        }
      ]
    }
  }
}
