{
  "gsd": {
    "metadata": {
      "type": "concern",
      "exploitCode": "unknown",
      "remediation": "official",
      "reportConfidence": "confirmed",
      "reporter": "tdunlap607",
      "reporter_id": "16122665"
    },
    "osvSchema": {
      "id": "GSD-2023-1004348",
      "modified": "2023-05-09T15:52:29.598738Z",
      "published": "2023-05-09T15:52:29.598738Z",
      "schema_version": "1.4.0",
      "summary": "unshiftio/url-parse: Incomplete string escaping or encoding",
      "details": "unshiftio/url-parse: Incomplete string escaping or encoding\n\nA string transformer that does not replace or escape all occurrences of a meta-character may be ineffective.\nThis is an automated ID intended to aid in discovery of potential security vulnerabilities. The actual impact and attack plausibility have not yet been proven.\nThis ID is fixed in unshiftio/url-parse version 1.5.2 by commit d2979b586d8c7751e0c77f127d9ce1b2143cc0c9. For more details please see the references link.",
      "affected": [
        {
          "package": {
            "name": "unshiftio/url-parse",
            "ecosystem": NaN
          },
          "ranges": [
            {
              "type": "GIT",
              "repo": "https://github.com/unshiftio/url-parse.git/",
              "events": [
                {
                  "introduced": "0"
                },
                {
                  "limit": "d2979b586d8c7751e0c77f127d9ce1b2143cc0c9"
                }
              ]
            },
            {
              "type": "SEMVER",
              "repo": "https://github.com/unshiftio/url-parse.git/",
              "events": [
                {
                  "introduced": "0"
                },
                {
                  "fixed": "1.5.2"
                }
              ]
            }
          ]
        }
      ],
      "references": [
        {
          "type": "FIXED",
          "url": "https://github.com/unshiftio/url-parse/commit/d2979b586d8c7751e0c77f127d9ce1b2143cc0c9"
        }
      ]
    }
  }
}
