{
  "gsd": {
    "metadata": {
      "type": "concern",
      "exploitCode": "unknown",
      "remediation": "official",
      "reportConfidence": "confirmed",
      "reporter": "joshbressers",
      "reporter_id": "1692786"
    },
    "osvSchema": {
      "id": "GSD-2023-1004246",
      "modified": "2023-05-08T16:16:06.483232Z",
      "published": "2023-05-08T16:16:06.483232Z",
      "schema_version": "1.4.0",
      "summary": "io_uring: fix memory leak when removing provided buffers",
      "details": "io_uring: fix memory leak when removing provided buffers\n\nThis is an automated ID intended to aid in discovery of potential security vulnerabilities. The actual impact and attack plausibility have not yet been proven.\nThis ID is fixed in Linux Kernel version v6.2.11 by commit c117c15927772d1624c29c092b6bd3f47c7faa48, it was introduced in version v5.18 by commit cc3cec8367cba76a8ae4c271eba8450f3efc1ba3. For more details please see the references link.",
      "affected": [
        {
          "package": {
            "name": "Kernel",
            "ecosystem": "Linux"
          },
          "ranges": [
            {
              "type": "GIT",
              "repo": "https://git.kernel.org/pub/scm/linux/kernel/git/stable/linux.git/",
              "events": [
                {
                  "introduced": "cc3cec8367cba76a8ae4c271eba8450f3efc1ba3"
                },
                {
                  "limit": "c117c15927772d1624c29c092b6bd3f47c7faa48"
                }
              ]
            }
          ]
        },
        {
          "package": {
            "name": "Kernel",
            "ecosystem": "Linux"
          },
          "ranges": [
            {
              "type": "SEMVER",
              "repo": "https://git.kernel.org/pub/scm/linux/kernel/git/stable/linux.git/",
              "events": [
                {
                  "introduced": "5.18"
                },
                {
                  "fixed": "6.2.11"
                }
              ]
            }
          ]
        }
      ],
      "references": [
        {
          "type": "WEB",
          "url": "https://git.kernel.org/pub/scm/linux/kernel/git/stable/linux.git/commit/?id=cc3cec8367cba76a8ae4c271eba8450f3efc1ba3"
        },
        {
          "type": "WEB",
          "url": "https://git.kernel.org/pub/scm/linux/kernel/git/stable/linux.git/commit/?id=c117c15927772d1624c29c092b6bd3f47c7faa48"
        }
      ]
    }
  }
}
