{
  "gsd": {
    "metadata": {
      "type": "concern",
      "exploitCode": "unknown",
      "remediation": "official",
      "reportConfidence": "confirmed",
      "reporter": "joshbressers",
      "reporter_id": "1692786"
    },
    "osvSchema": {
      "id": "GSD-2023-1004685",
      "modified": "2023-05-08T17:03:01.057275Z",
      "published": "2023-05-08T17:03:01.057275Z",
      "schema_version": "1.4.0",
      "summary": "ext4: Fix deadlock during directory rename",
      "details": "ext4: Fix deadlock during directory rename\n\nThis is an automated ID intended to aid in discovery of potential security vulnerabilities. The actual impact and attack plausibility have not yet been proven.\nThis ID is fixed in Linux Kernel version v6.1.20 by commit 2ef7f829214fa8f428d953b49557b89b2b02db66, it was introduced in version v6.1.20 by commit b0bb13612292ca90fa4c2a7e425375649bc50d3e. For more details please see the references link.",
      "affected": [
        {
          "package": {
            "name": "Kernel",
            "ecosystem": "Linux"
          },
          "ranges": [
            {
              "type": "GIT",
              "repo": "https://git.kernel.org/pub/scm/linux/kernel/git/stable/linux.git/",
              "events": [
                {
                  "introduced": "b0bb13612292ca90fa4c2a7e425375649bc50d3e"
                },
                {
                  "limit": "2ef7f829214fa8f428d953b49557b89b2b02db66"
                }
              ]
            }
          ]
        },
        {
          "package": {
            "name": "Kernel",
            "ecosystem": "Linux"
          },
          "ranges": [
            {
              "type": "SEMVER",
              "repo": "https://git.kernel.org/pub/scm/linux/kernel/git/stable/linux.git/",
              "events": [
                {
                  "introduced": "6.1.20"
                },
                {
                  "fixed": "6.1.20"
                }
              ]
            }
          ]
        }
      ],
      "references": [
        {
          "type": "WEB",
          "url": "https://git.kernel.org/pub/scm/linux/kernel/git/stable/linux.git/commit/?id=b0bb13612292ca90fa4c2a7e425375649bc50d3e"
        },
        {
          "type": "WEB",
          "url": "https://git.kernel.org/pub/scm/linux/kernel/git/stable/linux.git/commit/?id=2ef7f829214fa8f428d953b49557b89b2b02db66"
        }
      ]
    }
  }
}
