{
  "gsd": {
    "metadata": {
      "type": "concern",
      "exploitCode": "unknown",
      "remediation": "official",
      "reportConfidence": "confirmed",
      "reporter": "joshbressers",
      "reporter_id": "1692786"
    },
    "osvSchema": {
      "id": "GSD-2023-1004651",
      "modified": "2023-05-08T19:11:41.935813Z",
      "published": "2023-05-08T19:11:41.935813Z",
      "schema_version": "1.4.0",
      "summary": "net: usb: smsc75xx: Move packet length check to prevent kernel panic in skb_pull",
      "details": "net: usb: smsc75xx: Move packet length check to prevent kernel panic in skb_pull\n\nThis is an automated ID intended to aid in discovery of potential security vulnerabilities. The actual impact and attack plausibility have not yet been proven.\nThis ID is fixed in Linux Kernel version v6.1.21 by commit 4caee8e7d91e4f06f21881726da9c1bb2cd6e4fa, it was introduced in version v6.1.21 by commit c7bdc137ca163b90917c1eeba4f1937684bd4f8b. For more details please see the references link.",
      "affected": [
        {
          "package": {
            "name": "Kernel",
            "ecosystem": "Linux"
          },
          "ranges": [
            {
              "type": "GIT",
              "repo": "https://git.kernel.org/pub/scm/linux/kernel/git/stable/linux.git/",
              "events": [
                {
                  "introduced": "c7bdc137ca163b90917c1eeba4f1937684bd4f8b"
                },
                {
                  "limit": "4caee8e7d91e4f06f21881726da9c1bb2cd6e4fa"
                }
              ]
            },
            {
              "type": "SEMVER",
              "repo": "https://git.kernel.org/pub/scm/linux/kernel/git/stable/linux.git/",
              "events": [
                {
                  "introduced": "6.1.21"
                },
                {
                  "fixed": "6.1.21"
                }
              ]
            }
          ]
        }
      ],
      "references": [
        {
          "type": "INTRODUCED",
          "url": "https://git.kernel.org/pub/scm/linux/kernel/git/stable/linux.git/commit/?id=c7bdc137ca163b90917c1eeba4f1937684bd4f8b"
        },
        {
          "type": "FIXED",
          "url": "https://git.kernel.org/pub/scm/linux/kernel/git/stable/linux.git/commit/?id=4caee8e7d91e4f06f21881726da9c1bb2cd6e4fa"
        }
      ]
    }
  }
}
