{
  "gsd": {
    "metadata": {
      "type": "concern",
      "exploitCode": "unknown",
      "remediation": "official",
      "reportConfidence": "confirmed",
      "reporter": "joshbressers",
      "reporter_id": "1692786"
    },
    "osvSchema": {
      "id": "GSD-2023-1004869",
      "modified": "2023-05-08T17:24:59.539383Z",
      "published": "2023-05-08T17:24:59.539383Z",
      "schema_version": "1.4.0",
      "summary": "xtensa: fix KASAN report for show_stack",
      "details": "xtensa: fix KASAN report for show_stack\n\nThis is an automated ID intended to aid in discovery of potential security vulnerabilities. The actual impact and attack plausibility have not yet been proven.\nThis ID is fixed in Linux Kernel version v5.10.177 by commit 08bfd05987df2756aaf7b2b8f014c4cdcc6bcb39. For more details please see the references link.",
      "affected": [
        {
          "package": {
            "name": "Kernel",
            "ecosystem": "Linux"
          },
          "ranges": [
            {
              "type": "GIT",
              "repo": "https://git.kernel.org/pub/scm/linux/kernel/git/stable/linux.git/",
              "events": [
                {
                  "introduced": "0"
                },
                {
                  "limit": "08bfd05987df2756aaf7b2b8f014c4cdcc6bcb39"
                }
              ]
            }
          ]
        },
        {
          "package": {
            "name": "Kernel",
            "ecosystem": "Linux"
          },
          "ranges": [
            {
              "type": "SEMVER",
              "repo": "https://git.kernel.org/pub/scm/linux/kernel/git/stable/linux.git/",
              "events": [
                {
                  "introduced": "0"
                },
                {
                  "fixed": "5.10.177"
                }
              ]
            }
          ]
        }
      ],
      "references": [
        {
          "type": "WEB",
          "url": "https://git.kernel.org/pub/scm/linux/kernel/git/stable/linux.git/commit/?id=08bfd05987df2756aaf7b2b8f014c4cdcc6bcb39"
        }
      ]
    }
  }
}
