{
  "gsd": {
    "metadata": {
      "type": "concern",
      "exploitCode": "unknown",
      "remediation": "official",
      "reportConfidence": "confirmed",
      "reporter": "joshbressers",
      "reporter_id": "1692786"
    },
    "osvSchema": {
      "id": "GSD-2023-1008326",
      "modified": "2023-08-27T19:46:44.256486Z",
      "published": "2023-08-27T19:46:44.256486Z",
      "schema_version": "1.4.0",
      "summary": "xfrm: fix slab-use-after-free in decode_session6",
      "details": "xfrm: fix slab-use-after-free in decode_session6\n\nThis is an automated ID intended to aid in discovery of potential security vulnerabilities. The actual impact and attack plausibility have not yet been proven.\nThis ID is fixed in Linux Kernel version v5.10.192 by commit bafa236380816b41b2c4c6970d9067fefa4a6c9e, it was introduced in version v3.19 by commit f855691975bb06373a98711e4cfe2c224244b536. For more details please see the references link.",
      "affected": [
        {
          "package": {
            "name": "Kernel",
            "ecosystem": "Linux"
          },
          "ranges": [
            {
              "type": "GIT",
              "repo": "https://git.kernel.org/pub/scm/linux/kernel/git/stable/linux.git/",
              "events": [
                {
                  "introduced": "f855691975bb06373a98711e4cfe2c224244b536"
                },
                {
                  "limit": "bafa236380816b41b2c4c6970d9067fefa4a6c9e"
                }
              ]
            },
            {
              "type": "SEMVER",
              "repo": "https://git.kernel.org/pub/scm/linux/kernel/git/stable/linux.git/",
              "events": [
                {
                  "introduced": "3.19"
                },
                {
                  "fixed": "5.10.192"
                }
              ]
            }
          ]
        }
      ],
      "references": [
        {
          "type": "INTRODUCED",
          "url": "https://git.kernel.org/pub/scm/linux/kernel/git/stable/linux.git/commit/?id=f855691975bb06373a98711e4cfe2c224244b536"
        },
        {
          "type": "FIXED",
          "url": "https://git.kernel.org/pub/scm/linux/kernel/git/stable/linux.git/commit/?id=bafa236380816b41b2c4c6970d9067fefa4a6c9e"
        }
      ]
    }
  }
}
