{
  "gsd": {
    "metadata": {
      "type": "concern",
      "exploitCode": "unknown",
      "remediation": "official",
      "reportConfidence": "confirmed",
      "reporter": "joshbressers",
      "reporter_id": "1692786"
    },
    "osvSchema": {
      "id": "GSD-2023-1008253",
      "modified": "2023-08-27T19:38:30.369620Z",
      "published": "2023-08-27T19:38:30.369620Z",
      "schema_version": "1.4.0",
      "summary": "powerpc/rtas_flash: allow user copy to flash block cache objects",
      "details": "powerpc/rtas_flash: allow user copy to flash block cache objects\n\nThis is an automated ID intended to aid in discovery of potential security vulnerabilities. The actual impact and attack plausibility have not yet been proven.\nThis ID is fixed in Linux Kernel version v5.15.128 by commit 8ef25fb13494e35c6dbe15445c7875fa92bc3e8b, it was introduced in version v4.16 by commit 6d07d1cd300f4c7e16005f881fea388164999cc8. For more details please see the references link.",
      "affected": [
        {
          "package": {
            "name": "Kernel",
            "ecosystem": "Linux"
          },
          "ranges": [
            {
              "type": "GIT",
              "repo": "https://git.kernel.org/pub/scm/linux/kernel/git/stable/linux.git/",
              "events": [
                {
                  "introduced": "6d07d1cd300f4c7e16005f881fea388164999cc8"
                },
                {
                  "limit": "8ef25fb13494e35c6dbe15445c7875fa92bc3e8b"
                }
              ]
            },
            {
              "type": "SEMVER",
              "repo": "https://git.kernel.org/pub/scm/linux/kernel/git/stable/linux.git/",
              "events": [
                {
                  "introduced": "4.16"
                },
                {
                  "fixed": "5.15.128"
                }
              ]
            }
          ]
        }
      ],
      "references": [
        {
          "type": "INTRODUCED",
          "url": "https://git.kernel.org/pub/scm/linux/kernel/git/stable/linux.git/commit/?id=6d07d1cd300f4c7e16005f881fea388164999cc8"
        },
        {
          "type": "FIXED",
          "url": "https://git.kernel.org/pub/scm/linux/kernel/git/stable/linux.git/commit/?id=8ef25fb13494e35c6dbe15445c7875fa92bc3e8b"
        }
      ]
    }
  }
}
