{
  "gsd": {
    "metadata": {
      "type": "concern",
      "exploitCode": "unknown",
      "remediation": "official",
      "reportConfidence": "confirmed",
      "reporter": "joshbressers",
      "reporter_id": "1692786"
    },
    "osvSchema": {
      "id": "GSD-2023-1002819",
      "modified": "2023-04-05T00:31:35.935203Z",
      "published": "2023-04-05T00:31:35.935203Z",
      "schema_version": "1.4.0",
      "summary": "ubi: ensure that VID header offset + VID header size <= alloc, size",
      "details": "ubi: ensure that VID header offset + VID header size <= alloc, size\n\nThis is an automated ID intended to aid in discovery of potential security vulnerabilities. The actual impact and attack plausibility have not yet been proven.\nThis ID is fixed in Linux Kernel version v6.1.18 by commit 61aeba0e4b4124cfe3c5427feaf29c626dfa89e5, it was introduced in version v2.6.22 by commit 801c135ce73d5df1caf3eca35b66a10824ae0707. For more details please see the references link.",
      "affected": [
        {
          "package": {
            "name": "Kernel",
            "ecosystem": "Linux"
          },
          "ranges": [
            {
              "type": "GIT",
              "repo": "https://git.kernel.org/pub/scm/linux/kernel/git/stable/linux.git/",
              "events": [
                {
                  "introduced": "801c135ce73d5df1caf3eca35b66a10824ae0707"
                },
                {
                  "limit": "61aeba0e4b4124cfe3c5427feaf29c626dfa89e5"
                }
              ]
            }
          ]
        },
        {
          "package": {
            "name": "Kernel",
            "ecosystem": "Linux"
          },
          "ranges": [
            {
              "type": "SEMVER",
              "repo": "https://git.kernel.org/pub/scm/linux/kernel/git/stable/linux.git/",
              "events": [
                {
                  "introduced": "2.6.22"
                },
                {
                  "fixed": "6.1.18"
                }
              ]
            }
          ]
        }
      ],
      "references": [
        {
          "type": "WEB",
          "url": "https://git.kernel.org/pub/scm/linux/kernel/git/stable/linux.git/commit/?id=801c135ce73d5df1caf3eca35b66a10824ae0707"
        },
        {
          "type": "WEB",
          "url": "https://git.kernel.org/pub/scm/linux/kernel/git/stable/linux.git/commit/?id=61aeba0e4b4124cfe3c5427feaf29c626dfa89e5"
        }
      ]
    }
  }
}
