{
  "gsd": {
    "metadata": {
      "type": "concern",
      "exploitCode": "unknown",
      "remediation": "official",
      "reportConfidence": "confirmed",
      "reporter": "joshbressers",
      "reporter_id": "1692786"
    },
    "osvSchema": {
      "id": "GSD-2023-1007336",
      "modified": "2023-08-27T17:29:54.235100Z",
      "published": "2023-08-27T17:29:54.235100Z",
      "schema_version": "1.4.0",
      "summary": "igc: Fix Kernel Panic during ndo_tx_timeout callback",
      "details": "igc: Fix Kernel Panic during ndo_tx_timeout callback\n\nThis is an automated ID intended to aid in discovery of potential security vulnerabilities. The actual impact and attack plausibility have not yet been proven.\nThis ID is fixed in Linux Kernel version v6.1.43 by commit c09df09241fdd6aa5b94a5243369662a13ec608a, it was introduced in version v6.1.12 by commit 5f9c656ab2c4c36f3b85819c7a9a8bec5711cfb5. For more details please see the references link.",
      "affected": [
        {
          "package": {
            "name": "Kernel",
            "ecosystem": "Linux"
          },
          "ranges": [
            {
              "type": "GIT",
              "repo": "https://git.kernel.org/pub/scm/linux/kernel/git/stable/linux.git/",
              "events": [
                {
                  "introduced": "5f9c656ab2c4c36f3b85819c7a9a8bec5711cfb5"
                },
                {
                  "limit": "c09df09241fdd6aa5b94a5243369662a13ec608a"
                }
              ]
            },
            {
              "type": "SEMVER",
              "repo": "https://git.kernel.org/pub/scm/linux/kernel/git/stable/linux.git/",
              "events": [
                {
                  "introduced": "6.1.12"
                },
                {
                  "fixed": "6.1.43"
                }
              ]
            }
          ]
        }
      ],
      "references": [
        {
          "type": "INTRODUCED",
          "url": "https://git.kernel.org/pub/scm/linux/kernel/git/stable/linux.git/commit/?id=5f9c656ab2c4c36f3b85819c7a9a8bec5711cfb5"
        },
        {
          "type": "FIXED",
          "url": "https://git.kernel.org/pub/scm/linux/kernel/git/stable/linux.git/commit/?id=c09df09241fdd6aa5b94a5243369662a13ec608a"
        }
      ]
    }
  }
}
