{
  "gsd": {
    "metadata": {
      "type": "concern",
      "exploitCode": "unknown",
      "remediation": "official",
      "reportConfidence": "confirmed",
      "reporter": "joshbressers",
      "reporter_id": "1692786"
    },
    "osvSchema": {
      "id": "GSD-2023-1007607",
      "modified": "2023-08-27T18:03:39.310821Z",
      "published": "2023-08-27T18:03:39.310821Z",
      "schema_version": "1.4.0",
      "summary": "tracing/histograms: Add histograms to hist_vars if they have referenced variables",
      "details": "tracing/histograms: Add histograms to hist_vars if they have referenced variables\n\nThis is an automated ID intended to aid in discovery of potential security vulnerabilities. The actual impact and attack plausibility have not yet been proven.\nThis ID is fixed in Linux Kernel version v5.15.121 by commit 97f54b330c797ed27fba8791baeaa38ace886cbd, it was introduced in version v4.17 by commit 067fe038e70f6e64960d26a79c4df5f1413d0f13. For more details please see the references link.",
      "affected": [
        {
          "package": {
            "name": "Kernel",
            "ecosystem": "Linux"
          },
          "ranges": [
            {
              "type": "GIT",
              "repo": "https://git.kernel.org/pub/scm/linux/kernel/git/stable/linux.git/",
              "events": [
                {
                  "introduced": "067fe038e70f6e64960d26a79c4df5f1413d0f13"
                },
                {
                  "limit": "97f54b330c797ed27fba8791baeaa38ace886cbd"
                }
              ]
            },
            {
              "type": "SEMVER",
              "repo": "https://git.kernel.org/pub/scm/linux/kernel/git/stable/linux.git/",
              "events": [
                {
                  "introduced": "4.17"
                },
                {
                  "fixed": "5.15.121"
                }
              ]
            }
          ]
        }
      ],
      "references": [
        {
          "type": "INTRODUCED",
          "url": "https://git.kernel.org/pub/scm/linux/kernel/git/stable/linux.git/commit/?id=067fe038e70f6e64960d26a79c4df5f1413d0f13"
        },
        {
          "type": "FIXED",
          "url": "https://git.kernel.org/pub/scm/linux/kernel/git/stable/linux.git/commit/?id=97f54b330c797ed27fba8791baeaa38ace886cbd"
        }
      ]
    }
  }
}
